README.md
setup.cfg
setup.py
free_proxies_useragents/__init__.py
free_proxies_useragents/freeprx.py
free_proxies_useragents.egg-info/PKG-INFO
free_proxies_useragents.egg-info/SOURCES.txt
free_proxies_useragents.egg-info/dependency_links.txt
free_proxies_useragents.egg-info/entry_points.txt
free_proxies_useragents.egg-info/top_level.txt