Metadata-Version: 2.1
Name: free-proxies-useragents
Version: 1.0.1
Summary: free proxies and useragents, created by ebankoff
Home-page: https://github.com/ebankoff/free-proxies-and-useragents
Author: ebankoff
Author-email: herrnihilus@gmail.com
License: MIT
Platform: UNKNOWN
Requires-Python: >=3.5
